code_complexity_pro/__init__.py
code_complexity_pro/api_handler.py
code_complexity_pro/complexity_analyzer.py
code_complexity_pro/main.py
code_complexity_pro/utils.py
tests/__init__.py
tests/test_api_handler.py
tests/test_load_config.py
tests/test_utils.py
code_complexity_pro-1.1.2.dist-info/LICENSE
code_complexity_pro-1.1.2.dist-info/METADATA
code_complexity_pro-1.1.2.dist-info/WHEEL
code_complexity_pro-1.1.2.dist-info/entry_points.txt
code_complexity_pro-1.1.2.dist-info/top_level.txt
code_complexity_pro-1.1.2.dist-info/RECORD
