Metadata-Version: 2.1
Name: code_complexity_pro
Version: 1.1.2
Summary: A Python tool for analyzing code complexity
Home-page: https://github.com/yourusername/code-complexity-pro
Author: Madhur Saluja
Author-email: msaluja1@myseneca.ca
Classifier: Programming Language :: Python :: 3
Classifier: License :: OSI Approved :: MIT License
Classifier: Operating System :: OS Independent
Requires-Python: >=3.7
License-File: LICENSE
Requires-Dist: numpy>=1.20.0
Requires-Dist: pandas>=1.3.0
Requires-Dist: python-dotenv
Requires-Dist: toml
